ErisPulse_InfoQuery/Core.py
ErisPulse_InfoQuery/__init__.py
erispulse_infoquery-1.0.0.dist-info/licenses/LICENSE
erispulse_infoquery-1.0.0.dist-info/METADATA
erispulse_infoquery-1.0.0.dist-info/WHEEL
erispulse_infoquery-1.0.0.dist-info/entry_points.txt
erispulse_infoquery-1.0.0.dist-info/top_level.txt
erispulse_infoquery-1.0.0.dist-info/RECORD
