Metadata-Version: 2.4
Name: ErisPulse-InfoQuery
Version: 1.0.0
Summary: 信息统计查询模块，用于查询InfoStats收集的统计数据
Author-email: wsu2059q <wsu2059@qq.com>
License: Copyright 2025 wsu2059q
Project-URL: homepage, https://github.com/wsu2059q/ErisPulse-InfoQuery
Requires-Python: >=3.9
License-File: LICENSE
Dynamic: license-file
